[
  {
    "full_name": "mik3y/airdash",
    "stargazers_count": 34,
    "open_issues_count": 6,
    "forks_count": 1
  },
  {
    "full_name": "rsalmei/alive-progress",
    "stargazers_count": 2632,
    "open_issues_count": 24,
    "forks_count": 103
  },
  {
    "full_name": "willmcgugan/rich",
    "stargazers_count": 28539,
    "open_issues_count": 8,
    "forks_count": 876
  },
  {
    "full_name": "hediet/vscode-debug-visualizer",
    "stargazers_count": 7010,
    "open_issues_count": 43,
    "forks_count": 327
  },
  {
    "full_name": "chadgeary/cloudblock",
    "stargazers_count": 388,
    "open_issues_count": 1,
    "forks_count": 32
  },
  {
    "full_name": "vmstan/gravity-sync",
    "stargazers_count": 659,
    "open_issues_count": 17,
    "forks_count": 47
  },
  {
    "full_name": "docker/awesome-compose",
    "stargazers_count": 12682,
    "open_issues_count": 36,
    "forks_count": 1645
  },
  {
    "full_name": "sanathp/statusok",
    "stargazers_count": 1513,
    "open_issues_count": 41,
    "forks_count": 193
  },
  {
    "full_name": "Hammerspoon/hammerspoon",
    "stargazers_count": 8143,
    "open_issues_count": 392,
    "forks_count": 426
  },
  {
    "full_name": "chubin/wttr.in",
    "stargazers_count": 15493,
    "open_issues_count": 164,
    "forks_count": 744
  },
  {
    "full_name": "schachmat/wego",
    "stargazers_count": 6816,
    "open_issues_count": 42,
    "forks_count": 432
  },
  {
    "full_name": "timburgan/timburgan",
    "stargazers_count": 555,
    "open_issues_count": 110,
    "forks_count": 79
  },
  {
    "full_name": "samyk/awesome-raspberrypi",
    "stargazers_count": 167,
    "open_issues_count": 2,
    "forks_count": 40
  },
  {
    "full_name": "novnc/noVNC",
    "stargazers_count": 7956,
    "open_issues_count": 43,
    "forks_count": 1653
  },
  {
    "full_name": "elewin/pi-weather-station",
    "stargazers_count": 133,
    "open_issues_count": 5,
    "forks_count": 23
  },
  {
    "full_name": "jacobalberty/unifi-docker",
    "stargazers_count": 1215,
    "open_issues_count": 157,
    "forks_count": 323
  },
  {
    "full_name": "AdguardTeam/AdGuardHome",
    "stargazers_count": 8651,
    "open_issues_count": 400,
    "forks_count": 876
  },
  {
    "full_name": "mikenye/docker-readsb",
    "stargazers_count": 66,
    "open_issues_count": 0,
    "forks_count": 3
  },
  {
    "full_name": "wiedehopf/graphs1090",
    "stargazers_count": 183,
    "open_issues_count": 2,
    "forks_count": 21
  },
  {
    "full_name": "BurntSushi/ripgrep",
    "stargazers_count": 27007,
    "open_issues_count": 97,
    "forks_count": 1195
  },
  {
    "full_name": "wiedehopf/tar1090",
    "stargazers_count": 465,
    "open_issues_count": 14,
    "forks_count": 81
  },
  {
    "full_name": "dgiardini/rtl-ais",
    "stargazers_count": 196,
    "open_issues_count": 6,
    "forks_count": 68
  },
  {
    "full_name": "jivoi/awesome-osint",
    "stargazers_count": 7272,
    "open_issues_count": 4,
    "forks_count": 1608
  },
  {
    "full_name": "amiantos/pibar",
    "stargazers_count": 223,
    "open_issues_count": 17,
    "forks_count": 3
  },
  {
    "full_name": "Millefeuille42/covidTerm",
    "stargazers_count": 3,
    "open_issues_count": 0,
    "forks_count": 0
  },
  {
    "full_name": "Lissy93/personal-security-checklist",
    "stargazers_count": 2204,
    "open_issues_count": 7,
    "forks_count": 224
  },
  {
    "full_name": "joke2k/faker",
    "stargazers_count": 12980,
    "open_issues_count": 161,
    "forks_count": 1477
  },
  {
    "full_name": "debauchee/barrier",
    "stargazers_count": 13051,
    "open_issues_count": 624,
    "forks_count": 807
  },
  {
    "full_name": "lk-geimfari/mimesis",
    "stargazers_count": 3341,
    "open_issues_count": 7,
    "forks_count": 277
  },
  {
    "full_name": "BullsEye0/google_dork_list",
    "stargazers_count": 835,
    "open_issues_count": 1,
    "forks_count": 208
  }
]